[
    {
        "key": "dbln",
        "value": "%7B%22100088638475561%22%3A%226TcfqPVl%22%2C%2261554014382582%22%3A%22zjYwVs5G%22%2C%22100094500447255%22%3A%22Q1vOrlQg%22%7D",
        "domain": "facebook.com",
        "path": "/login/device-based/",
        "hostOnly": false,
        "creation": "2024-04-02T15:26:14.115Z",
        "lastAccessed": "2024-04-02T15:26:14.115Z"
    },
    {
        "key": "datr",
        "value": "0CHkZSXBAceQZLFEhfnUUlun",
        "domain": "facebook.com",
        "path": "/",
        "hostOnly": false,
        "creation": "2024-04-02T15:26:14.115Z",
        "lastAccessed": "2024-04-02T15:26:14.115Z"
    },
    {
        "key": "sb",
        "value": "0CHkZb8XJR0Ra6uAaK2Hc1Uu",
        "domain": "facebook.com",
        "path": "/",
        "hostOnly": false,
        "creation": "2024-04-02T15:26:14.115Z",
        "lastAccessed": "2024-04-02T15:26:14.115Z"
    },
    {
        "key": "ps_n",
        "value": "0",
        "domain": "facebook.com",
        "path": "/",
        "hostOnly": false,
        "creation": "2024-04-02T15:26:14.115Z",
        "lastAccessed": "2024-04-02T15:26:14.115Z"
    },
    {
        "key": "ps_l",
        "value": "0",
        "domain": "facebook.com",
        "path": "/",
        "hostOnly": false,
        "creation": "2024-04-02T15:26:14.115Z",
        "lastAccessed": "2024-04-02T15:26:14.115Z"
    },
    {
        "key": "locale",
        "value": "en_GB",
        "domain": "facebook.com",
        "path": "/",
        "hostOnly": false,
        "creation": "2024-04-02T15:26:14.115Z",
        "lastAccessed": "2024-04-02T15:26:14.115Z"
    },
    {
        "key": "m_pixel_ratio",
        "value": "2.934335231781006",
        "domain": "facebook.com",
        "path": "/",
        "hostOnly": false,
        "creation": "2024-04-02T15:26:14.115Z",
        "lastAccessed": "2024-04-02T15:26:14.115Z"
    },
    {
        "key": "wd",
        "value": "369x722",
        "domain": "facebook.com",
        "path": "/",
        "hostOnly": false,
        "creation": "2024-04-02T15:26:14.115Z",
        "lastAccessed": "2024-04-02T15:26:14.115Z"
    },
    {
        "key": "fr",
        "value": "0b3r01ZfkD6wZnarc.AWXFyz2uR809XM011dNb1JjPMLs.Bl5CHQ..AAA.0.0.BmDCLo.AWV4x6DspPw",
        "domain": "facebook.com",
        "path": "/",
        "hostOnly": false,
        "creation": "2024-04-02T15:26:14.115Z",
        "lastAccessed": "2024-04-02T15:26:14.115Z"
    },
    {
        "key": "c_user",
        "value": "100088638475561",
        "domain": "facebook.com",
        "path": "/",
        "hostOnly": false,
        "creation": "2024-04-02T15:26:14.115Z",
        "lastAccessed": "2024-04-02T15:26:14.115Z"
    },
    {
        "key": "xs",
        "value": "40%3AcjE2j8LXnEtEPg%3A2%3A1712071400%3A-1%3A5903",
        "domain": "facebook.com",
        "path": "/",
        "hostOnly": false,
        "creation": "2024-04-02T15:26:14.115Z",
        "lastAccessed": "2024-04-02T15:26:14.115Z"
    },
    {
        "key": "m_page_voice",
        "value": "100088638475561",
        "domain": "facebook.com",
        "path": "/",
        "hostOnly": false,
        "creation": "2024-04-02T15:26:14.115Z",
        "lastAccessed": "2024-04-02T15:26:14.115Z"
    },
    {
        "key": "wl_cbv",
        "value": "v2%3Bclient_version%3A2454%3Btimestamp%3A1712071570",
        "domain": "facebook.com",
        "path": "/",
        "hostOnly": false,
        "creation": "2024-04-02T15:26:14.115Z",
        "lastAccessed": "2024-04-02T15:26:14.115Z"
    },
    {
        "key": "vpd",
        "value": "v1%3B722x368x2.934335231781006",
        "domain": "facebook.com",
        "path": "/",
        "hostOnly": false,
        "creation": "2024-04-02T15:26:14.115Z",
        "lastAccessed": "2024-04-02T15:26:14.115Z"
    }
]
