[
    {
        "key": "dbln",
        "value": "%7B%22100088638475561%22%3A%227UPNXLcN%22%2C%2261554014382582%22%3A%22CjgENEvS%22%7D",
        "domain": "facebook.com",
        "path": "/login/device-based/",
        "hostOnly": false,
        "creation": "2024-04-19T15:54:49.763Z",
        "lastAccessed": "2024-04-19T15:54:49.763Z"
    },
    {
        "key": "datr",
        "value": "L1ERZpX8GPZZ9hJO5baVNb83",
        "domain": "facebook.com",
        "path": "/",
        "hostOnly": false,
        "creation": "2024-04-19T15:54:49.763Z",
        "lastAccessed": "2024-04-19T15:54:49.763Z"
    },
    {
        "key": "sb",
        "value": "L1ERZoiUssDPfJnbM2s9RQN5",
        "domain": "facebook.com",
        "path": "/",
        "hostOnly": false,
        "creation": "2024-04-19T15:54:49.763Z",
        "lastAccessed": "2024-04-19T15:54:49.763Z"
    },
    {
        "key": "dpr",
        "value": "3.2261457443237305",
        "domain": "facebook.com",
        "path": "/",
        "hostOnly": false,
        "creation": "2024-04-19T15:54:49.763Z",
        "lastAccessed": "2024-04-19T15:54:49.763Z"
    },
    {
        "key": "locale",
        "value": "en_GB",
        "domain": "facebook.com",
        "path": "/",
        "hostOnly": false,
        "creation": "2024-04-19T15:54:49.763Z",
        "lastAccessed": "2024-04-19T15:54:49.763Z"
    },
    {
        "key": "ps_n",
        "value": "1",
        "domain": "facebook.com",
        "path": "/",
        "hostOnly": false,
        "creation": "2024-04-19T15:54:49.763Z",
        "lastAccessed": "2024-04-19T15:54:49.763Z"
    },
    {
        "key": "ps_l",
        "value": "1",
        "domain": "facebook.com",
        "path": "/",
        "hostOnly": false,
        "creation": "2024-04-19T15:54:49.763Z",
        "lastAccessed": "2024-04-19T15:54:49.763Z"
    },
    {
        "key": "m_pixel_ratio",
        "value": "2.934335231781006",
        "domain": "facebook.com",
        "path": "/",
        "hostOnly": false,
        "creation": "2024-04-19T15:54:49.763Z",
        "lastAccessed": "2024-04-19T15:54:49.763Z"
    },
    {
        "key": "wd",
        "value": "369x527",
        "domain": "facebook.com",
        "path": "/",
        "hostOnly": false,
        "creation": "2024-04-19T15:54:49.763Z",
        "lastAccessed": "2024-04-19T15:54:49.763Z"
    },
    {
        "key": "fr",
        "value": "0BfgMuWyinxX2ctAk.AWXU0cUO-8hzo7SqHK4q0rb1ols.BmEVEv..AAA.0.0.BmIpO7.AWVOnWnCVWE",
        "domain": "facebook.com",
        "path": "/",
        "hostOnly": false,
        "creation": "2024-04-19T15:54:49.763Z",
        "lastAccessed": "2024-04-19T15:54:49.763Z"
    },
    {
        "key": "c_user",
        "value": "100094500447255",
        "domain": "facebook.com",
        "path": "/",
        "hostOnly": false,
        "creation": "2024-04-19T15:54:49.763Z",
        "lastAccessed": "2024-04-19T15:54:49.763Z"
    },
    {
        "key": "xs",
        "value": "4%3ACZMuvqWLgZwmGw%3A2%3A1713542077%3A-1%3A5903",
        "domain": "facebook.com",
        "path": "/",
        "hostOnly": false,
        "creation": "2024-04-19T15:54:49.763Z",
        "lastAccessed": "2024-04-19T15:54:49.763Z"
    },
    {
        "key": "fbl_st",
        "value": "101030247%3BT%3A28559034",
        "domain": "facebook.com",
        "path": "/",
        "hostOnly": false,
        "creation": "2024-04-19T15:54:49.763Z",
        "lastAccessed": "2024-04-19T15:54:49.763Z"
    },
    {
        "key": "wl_cbv",
        "value": "v2%3Bclient_version%3A2472%3Btimestamp%3A1713542078",
        "domain": "facebook.com",
        "path": "/",
        "hostOnly": false,
        "creation": "2024-04-19T15:54:49.763Z",
        "lastAccessed": "2024-04-19T15:54:49.763Z"
    },
    {
        "key": "vpd",
        "value": "v1%3B527x368x2.934335231781006",
        "domain": "facebook.com",
        "path": "/",
        "hostOnly": false,
        "creation": "2024-04-19T15:54:49.763Z",
        "lastAccessed": "2024-04-19T15:54:49.763Z"
    },
    {
        "key": "m_page_voice",
        "value": "100094500447255",
        "domain": "facebook.com",
        "path": "/",
        "hostOnly": false,
        "creation": "2024-04-19T15:54:49.763Z",
        "lastAccessed": "2024-04-19T15:54:49.763Z"
    }
]
